fastapi_vo/__init__.py
fastapi_vo/utils.py
FastAPI_VO-0.1.4.dist-info/LICENSE
FastAPI_VO-0.1.4.dist-info/METADATA
FastAPI_VO-0.1.4.dist-info/WHEEL
FastAPI_VO-0.1.4.dist-info/top_level.txt
FastAPI_VO-0.1.4.dist-info/RECORD
